{
  "project_info": {
    "project_number": "656631009880",
    "project_id": "jackienotes",
    "storage_bucket": "jackienotes.appspot.com"
  },
  "client": [
    {
      "client_info": {
        "mobilesdk_app_id": "1:656631009880:android:94d1a484c10f4aa732b02d",
        "android_client_info": {
          "package_name": "com.example.basic_registration_form"
        }
      },
      "oauth_client": [],
      "api_key": [
        {
          "current_key": "AIzaSyD-WQdTTuM_cIol9LNewJ4MGKybQEq0RLA"
        }
      ],
      "services": {
        "appinvite_service": {
          "other_platform_oauth_client": []
        }
      }
    },
    {
      "client_info": {
        "mobilesdk_app_id": "1:656631009880:android:23288593734d5c4c32b02d",
        "android_client_info": {
          "package_name": "com.example.flutter_application_1"
        }
      },
      "oauth_client": [],
      "api_key": [
        {
          "current_key": "AIzaSyD-WQdTTuM_cIol9LNewJ4MGKybQEq0RLA"
        }
      ],
      "services": {
        "appinvite_service": {
          "other_platform_oauth_client": []
        }
      }
    }
  ],
  "configuration_version": "1"
}